swing/__init__.py
swing/exceptions.py
swing/flusher.py
swing/formatter.py
swing/handler.py
swing/logger.py
swing/sender.py
swing_python_handler-1.0.0.dist-info/METADATA
swing_python_handler-1.0.0.dist-info/WHEEL
swing_python_handler-1.0.0.dist-info/top_level.txt
swing_python_handler-1.0.0.dist-info/RECORD
